{
  "$schema": "../gen/schemas/desktop-schema.json",
  "identifier": "default",
  "description": "Default capabilities for Speech AI Tool",
  "windows": ["main"],
  "permissions": [
    "core:default",
    "core:window:default",
    "core:window:allow-close",
    "core:window:allow-show",
    "core:window:allow-hide",
    "store:default",
    "clipboard-manager:default",
    "clipboard-manager:allow-write-text",
    "clipboard-manager:allow-read-text",
    "global-shortcut:default",
    "global-shortcut:allow-register",
    "global-shortcut:allow-unregister"
  ]
}
